pyxelist/V0_0.py
pyxelist/V0_1.py
pyxelist/V0_2.py
pyxelist/V0_3.py
pyxelist/__init__.py
pyxelist-0.3.0.dist-info/licenses/LICENSE
pyxelist-0.3.0.dist-info/METADATA
pyxelist-0.3.0.dist-info/WHEEL
pyxelist-0.3.0.dist-info/top_level.txt
pyxelist-0.3.0.dist-info/RECORD
