Metadata-Version: 2.4
Name: pyxelist
Version: 0.3.0
Summary: A small Python library for drawing grid-based graphics using turtle.
Author-email: Yanlin522 <you@example.com>
License: MIT
Keywords: turtle,grid,graphics,pyxel,2D
Classifier: Programming Language :: Python :: 3
Classifier: License :: OSI Approved :: MIT License
Classifier: Operating System :: OS Independent
Classifier: Topic :: Games/Entertainment
Classifier: Topic :: Software Development :: Libraries
Requires-Python: >=3.10
License-File: LICENSE
Dynamic: license-file
